[
{"name":"Children 1 9Ã","points":41},
{"name":"Children 2 9Ã","points":24},
{"name":"Children 3 9Ã","points":8},
{"name":"Children 4 9Ã","points":6},
{"name":"Children 5 9Ã","points":44},
{"name":"Children 6 9Ã","points":6},
{"name":"Children 7 9Ã","points":0},
{"name":"Children 8 9Ã","points":14},
{"name":"Children 9 9Ã","points":23},
{"name":"Children 10 9Ã","points":2},
{"name":"Children 11 9Ã","points":27},
{"name":"Children 12 9Ã","points":4},
{"name":"Children 13 9Ã","points":44},
{"name":"Children 14 9Ã","points":7},
{"name":"Children 15 9Ã","points":5},
{"name":"Children 16 9Ã","points":36},
{"name":"Children 17 9Ã","points":11},
{"name":"Children 18 9Ã","points":5},
{"name":"Children 19 9Ã","points":4},
{"name":"Children 20 9Ã","points":30},
{"name":"Children 21 9Ã","points":38},
{"name":"Children 22 9Ã","points":17},
{"name":"Children 23 9Ã","points":3},
{"name":"Children 24 9Ã","points":31},
{"name":"Children 25 9Ã","points":29}
]